joern_slice/__init__.py
joern_slice/cv_extract.py
joern_slice-0.1.1.dist-info/METADATA
joern_slice-0.1.1.dist-info/WHEEL
joern_slice-0.1.1.dist-info/RECORD
