Metadata-Version: 2.1
Name: joern-slice
Version: 0.1.1
Summary: 
Author: Your Name
Author-email: 2278594051@qq.com
Requires-Python: >=3.11,<4.0
Classifier: Programming Language :: Python :: 3
Classifier: Programming Language :: Python :: 3.11
Classifier: Programming Language :: Python :: 3.12
